shouty.py
django_shouty_templates-0.2.0.dist-info/LICENSE
django_shouty_templates-0.2.0.dist-info/METADATA
django_shouty_templates-0.2.0.dist-info/WHEEL
django_shouty_templates-0.2.0.dist-info/top_level.txt
django_shouty_templates-0.2.0.dist-info/RECORD
