Metadata-Version: 2.1
Name: django-shouty-templates
Version: 0.2.0
Summary: Applies a monkeypatch which forces Django's template language to error far more loudly about invalid assumptions
Home-page: https://github.com/kezabelle/django-shouty-templates
Author: Keryn Knight
Author-email: django-shouty-templates@kerynknight.com
Maintainer: Keryn Knight
Maintainer-email: django-shouty-templates@kerynknight.com
License: BSD License
Keywords: django templates DTL exception
Platform: UNKNOWN
Classifier: Development Status :: 3 - Alpha
Classifier: Intended Audience :: Developers
Classifier: License :: OSI Approved :: BSD License
Classifier: Natural Language :: English
Classifier: Programming Language :: Python
Classifier: Programming Language :: Python :: 2
Classifier: Programming Language :: Python :: 2.7
Classifier: Programming Language :: Python :: 3
Classifier: Programming Language :: Python :: 3.5
Classifier: Programming Language :: Python :: 3.6
Classifier: Framework :: Django
License-File: LICENSE
Requires-Dist: Django (>=1.9)
